unittests/__init__.py
unittests/test_py_utils.py
unittests/test_api_controller/__init__.py
unittests/test_api_controller/test_configman.py
unittests/test_queries/__init__.py
unittests/test_queries/test_contact_violations.py
unittests/test_queries/test_email_audit.py
unittests/test_queries/test_game_player_rel.py
unittests/test_queries/test_game_queries.py
unittests/test_queries/test_health_check.py
unittests/test_queries/test_logins_table_queries.py
unittests/test_queries/test_player_queries.py
unittests/test_queries/test_site_captcha_queries.py
utils_package/__init__.py
utils_package/definitions.py
utils_package/api_controller/__init__.py
utils_package/api_controller/configman.py
utils_package/data_controller/__init__.py
utils_package/data_controller/data_configs.py
utils_package/data_controller/json_config.py
utils_package/data_controller/pg_util.py
utils_package/data_controller/query_tools.py
utils_package/data_controller/scripts/__init__.py
utils_package/data_controller/scripts/health_check.py
utils_package/data_controller/scripts/captcha_cookie/__init__.py
utils_package/data_controller/scripts/captcha_cookie/site_captcha_results_queries.py
utils_package/data_controller/scripts/catan/__init__.py
utils_package/data_controller/scripts/catan/game_player_rel.py
utils_package/data_controller/scripts/catan/games_queries.py
utils_package/data_controller/scripts/catan/player_queries.py
utils_package/data_controller/scripts/email_controller/__init__.py
utils_package/data_controller/scripts/email_controller/contact_violations_queries.py
utils_package/data_controller/scripts/email_controller/email_audit_queries.py
utils_package/data_controller/scripts/site_queries/__init__.py
utils_package/data_controller/scripts/site_queries/logins_table.py
utils_package/py_utils/__init__.py
utils_package/py_utils/encryption_tool.py
utils_package/py_utils/logger.py
utils_package/py_utils/primary_utils.py
jbtech_utils_package-0.0.22.dist-info/LICENSE
jbtech_utils_package-0.0.22.dist-info/METADATA
jbtech_utils_package-0.0.22.dist-info/WHEEL
jbtech_utils_package-0.0.22.dist-info/top_level.txt
jbtech_utils_package-0.0.22.dist-info/RECORD
