Metadata-Version: 2.1
Name: jbtech-utils-package
Version: 0.0.22
Summary: Package for just basic utitilies
Home-page: https://github.com/jamberin/jbtech-utils-package
Author: James Beringer
Author-email: jamberin@gmail.com
License: UNKNOWN
Platform: UNKNOWN
Classifier: Programming Language :: Python :: 3.7
Classifier: Development Status :: 2 - Pre-Alpha
Classifier: License :: Public Domain
